Metadata-Version: 2.1
Name: climalite
Version: 2.0.0
Summary: weather forcast data
Home-page: https://github.com/Michael-Bitz/climalite
Author-email: MichaelBitzDev@gmail.com
License: MIT
Keywords: weather,forecast,openweather
Classifier: Development Status :: 3 - Alpha
Classifier: Intended Audience :: Developers
Classifier: Topic :: Software Development :: Build Tools
Classifier: License :: OSI Approved :: MIT License
Classifier: Programming Language :: Python :: 3.5
Classifier: Programming Language :: Python :: 3.6
Classifier: Programming Language :: Python :: 3.7
Classifier: Programming Language :: Python :: 3.8
